bluedot_rest_framework/__init__.py
bluedot_rest_framework/apps.py
bluedot_rest_framework/settings.py
bluedot_rest_framework/analysis/__init__.py
bluedot_rest_framework/analysis/apps.py
bluedot_rest_framework/analysis/tests.py
bluedot_rest_framework/analysis/urls.py
bluedot_rest_framework/analysis/migrations/__init__.py
bluedot_rest_framework/analysis/monitor/__init__.py
bluedot_rest_framework/analysis/monitor/models.py
bluedot_rest_framework/analysis/monitor/serializers.py
bluedot_rest_framework/analysis/monitor/views.py
bluedot_rest_framework/analysis/monitor/migrations/__init__.py
bluedot_rest_framework/api_auth/__init__.py
bluedot_rest_framework/api_auth/apps.py
bluedot_rest_framework/api_auth/models.py
bluedot_rest_framework/api_auth/serializers.py
bluedot_rest_framework/api_auth/urls.py
bluedot_rest_framework/api_auth/views.py
bluedot_rest_framework/api_auth/migrations/__init__.py
bluedot_rest_framework/api_auth/permission/__init__.py
bluedot_rest_framework/api_auth/permission/urls.py
bluedot_rest_framework/api_auth/permission/views.py
bluedot_rest_framework/api_auth/permission/__pycache__/__init__.cpython-38.pyc
bluedot_rest_framework/api_auth/permission/__pycache__/urls.cpython-38.pyc
bluedot_rest_framework/api_auth/permission/__pycache__/views.cpython-38.pyc
bluedot_rest_framework/category/__init__.py
bluedot_rest_framework/category/apps.py
bluedot_rest_framework/category/models.py
bluedot_rest_framework/category/serializers.py
bluedot_rest_framework/category/urls.py
bluedot_rest_framework/category/views.py
bluedot_rest_framework/category/migrations/__init__.py
bluedot_rest_framework/celery_tasks/__init__.py
bluedot_rest_framework/celery_tasks/config.py
bluedot_rest_framework/celery_tasks/main.py
bluedot_rest_framework/celery_tasks/settings.py
bluedot_rest_framework/celery_tasks/__pycache__/__init__.cpython-38.pyc
bluedot_rest_framework/celery_tasks/__pycache__/config.cpython-38.pyc
bluedot_rest_framework/celery_tasks/__pycache__/main.cpython-38.pyc
bluedot_rest_framework-2.2.90.dist-info/LICENSE.md
bluedot_rest_framework-2.2.90.dist-info/METADATA
bluedot_rest_framework-2.2.90.dist-info/WHEEL
bluedot_rest_framework-2.2.90.dist-info/top_level.txt
bluedot_rest_framework-2.2.90.dist-info/zip-safe
bluedot_rest_framework-2.2.90.dist-info/RECORD
