Metadata-Version: 2.1
Name: bluedot-rest-framework
Version: 2.2.90
Summary: UNKNOWN
Home-page: UNKNOWN
Author: UNKNOWN
Author-email: UNKNOWN
License: UNKNOWN
Platform: UNKNOWN
Requires-Dist: psycopg2
Requires-Dist: django
Requires-Dist: djangorestframework
Requires-Dist: djangorestframework-jwt
Requires-Dist: redis
Requires-Dist: uwsgi
Requires-Dist: oss2
Requires-Dist: pdf2image
Requires-Dist: channels (==2.4)
Requires-Dist: channels-redis (==2.4.2)
Requires-Dist: wechatpy
Requires-Dist: websocket-client
Requires-Dist: celery
Requires-Dist: xlwt
Requires-Dist: django-redis
Requires-Dist: yunpian-python-sdk
